ccg_logging/__init__.py
ccg_logging/ccg_logging.py
ccg_logging-1.4.2.dist-info/METADATA
ccg_logging-1.4.2.dist-info/WHEEL
ccg_logging-1.4.2.dist-info/licenses/LICENSE
ccg_logging-1.4.2.dist-info/RECORD
