Metadata-Version: 2.3
Name: ccg_logging
Version: 1.4.2
Summary: A package for function-driven logging.
Author-email: Rob Wade <rwade@claimsconsortiumgroup.co.uk>
License-File: LICENSE
Classifier: License :: OSI Approved :: MIT License
Classifier: Operating System :: OS Independent
Classifier: Programming Language :: Python :: 3
Requires-Python: >=3.11
Requires-Dist: loguru
Requires-Dist: pandas
